crystal_small
