Metadata-Version: 2.1
Name: crystal-small
Version: 2022.7.28
Summary: Everaldo's Crystal icons (small sizes) bundled for direct consumption from applications
Home-page: http://www.everaldo.com/crystal/
Author: Everaldo Coehlo, Lukasz Langa
Author-email: contact@everaldo.com, lukasz@langa.pl
License: LGPL
Keywords: small crystal icons everaldo lgpl static
Platform: any
Classifier: Development Status :: 6 - Mature
Classifier: Intended Audience :: Developers
Classifier: License :: OSI Approved :: GNU Library or Lesser General Public License (LGPL)
Classifier: Natural Language :: English
Classifier: Operating System :: OS Independent
Classifier: Programming Language :: Python
Classifier: Programming Language :: Python :: 2.5
Classifier: Programming Language :: Python :: 2.6
Classifier: Programming Language :: Python :: 2.7
Classifier: Topic :: Internet :: WWW/HTTP
Classifier: Topic :: Multimedia :: Graphics
Classifier: Topic :: Software Development :: Libraries :: Python Modules
License-File: COPYING.rst
